ryax/__init__.py
ryax/command_line.py
ryax/ryax_metadata/__init__.py
ryax/ryax_metadata/entities.py
ryax/ryax_metadata/ryax_metadata.py
ryax/triggers/__init__.py
ryax/triggers/protocols.py
ryax/utils/__init__.py
ryax/utils/check.py
ryax/utils/exceptions.py
ryax-0.0.3.dist-info/LICENSE.txt
ryax-0.0.3.dist-info/METADATA
ryax-0.0.3.dist-info/WHEEL
ryax-0.0.3.dist-info/entry_points.txt
ryax-0.0.3.dist-info/RECORD
