Metadata-Version: 2.1
Name: ryax
Version: 0.0.3
Summary: Ryax is an open-source platform that streamlines the design, deployment, and monitoring of Cloud automations and APIs.
License: MPL-2.0
Author: Charles Marshall
Author-email: charlesmarshallj@gmail.com
Requires-Python: >=3.10,<4.0
Classifier: License :: OSI Approved
Classifier: Programming Language :: Python :: 3
Classifier: Programming Language :: Python :: 3.10
Classifier: Programming Language :: Python :: 3.11
Requires-Dist: jsonschema (>=4.21.1,<5.0.0)
Requires-Dist: pillow (>=10.3.0,<11.0.0)
Requires-Dist: pyyaml (>=6.0.1,<7.0.0)
Requires-Dist: termcolor (>=2.4.0,<3.0.0)
Requires-Dist: typer[all] (>=0.9.0,<0.10.0)
Requires-Dist: types-jsonschema (>=4.21.0.20240331,<5.0.0.0)
Requires-Dist: types-pyyaml (>=6.0.12.20240311,<7.0.0.0)
